{
  "generator-jhipster": {
    "promptValues": {
      "packageName": "com.github.lucaseo90.worldgdp",
      "nativeLanguage": "en"
    },
    "jhipsterVersion": "6.10.3",
    "applicationType": "monolith",
    "baseName": "worldgdp",
    "packageName": "com.github.lucaseo90.worldgdp",
    "packageFolder": "com/github/lucaseo90/worldgdp",
    "serverPort": "8080",
    "authenticationType": "session",
    "cacheProvider": "ehcache",
    "enableHibernateCache": true,
    "websocket": false,
    "databaseType": "sql",
    "devDatabaseType": "h2Disk",
    "prodDatabaseType": "mysql",
    "searchEngine": false,
    "messageBroker": false,
    "serviceDiscoveryType": false,
    "buildTool": "maven",
    "enableSwaggerCodegen": false,
    "rememberMeKey": "461660d652e9e64e6181a8545a0e419d46930da6b26e1932b0150625af686cb19969ed6f2fadf1fd4b4ddc1c39cf71ac1183",
    "embeddableLaunchScript": false,
    "useSass": true,
    "clientPackageManager": "npm",
    "clientFramework": "vue",
    "clientTheme": "none",
    "clientThemeVariant": "",
    "creationTimestamp": 1604437670097,
    "testFrameworks": [],
    "jhiPrefix": "jhi",
    "entitySuffix": "",
    "dtoSuffix": "DTO",
    "otherModules": [
      {
        "name": "generator-jhipster-vuejs",
        "version": "1.9.2"
      }
    ],
    "enableTranslation": true,
    "nativeLanguage": "en",
    "languages": ["en", "ko"],
    "blueprints": [
      {
        "name": "generator-jhipster-vuejs",
        "version": "1.9.2"
      }
    ]
  }
}
